README.rst
setup.py
OTRXMPPChannel.egg-info/PKG-INFO
OTRXMPPChannel.egg-info/SOURCES.txt
OTRXMPPChannel.egg-info/dependency_links.txt
OTRXMPPChannel.egg-info/requires.txt
OTRXMPPChannel.egg-info/top_level.txt
otrxmppchannel/__init__.py
otrxmppchannel/connection.py
otrxmppchannel/otrmodule.py