Metadata-Version: 1.1
Name: OTRXMPPChannel
Version: 1.0.4
Summary: An OTR-XMPP communications channel
Home-page: https://github.com/mikegogulski/python-otrxmppchannel
Author: Mike Gogulski
Author-email: mike@gogulski.com
License: Unlicense
Platform: UNKNOWN
Classifier: Development Status :: 4 - Beta
Classifier: Intended Audience :: Developers
Classifier: License :: Public Domain
Classifier: Operating System :: OS Independent
Classifier: Programming Language :: Python
Classifier: Topic :: Communications :: Chat
Classifier: Topic :: Software Development :: Libraries :: Python Modules
